setup.cfg
setup.py
flipkart/__init__.py
flipkart/api.py
flipkart_api.egg-info/PKG-INFO
flipkart_api.egg-info/SOURCES.txt
flipkart_api.egg-info/dependency_links.txt
flipkart_api.egg-info/requires.txt
flipkart_api.egg-info/top_level.txt