Metadata-Version: 1.1
Name: flipkart-api
Version: 0.3
Summary: Flipkart affilate api 
Home-page: https://github.com/sidj242/flipkart-affiliate-api
Author: Siddharh Jain
Author-email: sidj242@gmail.com
License: UNKNOWN
Download-URL: https://github.com/sidj242/flipkart-affiliate-api/tarball/0.1
Keywords: flipkart,affilate,api
Platform: UNKNOWN
